cps_client/__init__.py
cps_client/cli.py
cps_client/api/__init__.py
cps_client/api/api.py
cps_client/api/configuration.py
cps_client/api/subscription.py
cps_client/api/transfer.py
cps_client/api/wallet.py
tests/__init__.py
tests/integration/__init__.py
tests/integration/test_integration.py
cps_client-0.1.13.dist-info/LICENSE.md
cps_client-0.1.13.dist-info/METADATA
cps_client-0.1.13.dist-info/WHEEL
cps_client-0.1.13.dist-info/entry_points.txt
cps_client-0.1.13.dist-info/top_level.txt
cps_client-0.1.13.dist-info/RECORD
