Metadata-Version: 2.1
Name: cps-client
Version: 0.1.13
Summary: A Circle Platform Services Python Client
Home-page: https://github.com/belljustin/cps-client-python
Author: J.D. Bell
Author-email: justin.bell@mail.mcgill.ca
License: UNKNOWN
Platform: UNKNOWN
Requires-Dist: click (==7.1.1)
Requires-Dist: requests (==2.23.0)
